MongoDBBSONLibrary/__init__.py
MongoDBBSONLibrary/mongo_connection_manager.py
MongoDBBSONLibrary/mongoquery.py
MongoDBBSONLibrary/version.py
robotframework_mongodb_bson_library-1.1.dist-info/LICENSE
robotframework_mongodb_bson_library-1.1.dist-info/METADATA
robotframework_mongodb_bson_library-1.1.dist-info/WHEEL
robotframework_mongodb_bson_library-1.1.dist-info/top_level.txt
robotframework_mongodb_bson_library-1.1.dist-info/RECORD
