Metadata-Version: 2.1
Name: robotframework-mongodb-bson-library
Version: 1.1
Summary: Mongo Database utility library for Robot Framework that uses bson serialization utils
Home-page: https://github.com/momenh/robotframework-mongodb-bson-library
Author: momen heragi
Author-email: momenh@gmail.com
License: Copyright (c) 2011, The Arizona Board of Regents on behalf of
Keywords: mongodb,robotframework,robotframework-mongodb-bson-library,MongoDBBSONLibrary
Platform: UNKNOWN
Classifier: Development Status :: 5 - Production/Stable
Classifier: License :: Public Domain
Classifier: Operating System :: OS Independent
Classifier: Programming Language :: Python
Classifier: Topic :: Software Development :: Testing
License-File: LICENSE
Requires-Dist: tox (>=3.0.0)
Requires-Dist: coverage
Requires-Dist: robotframework (>=3.0)
Requires-Dist: pymongo (>=3.8.0)
Requires-Dist: bson (>=0.5.8)
